rancher/__init__.py
rancher/base.py
rancher/cluster.py
rancher/project.py
rancher/service.py
rancher/stack.py
rancher/workload.py
rancher_api-0.3.0.dist-info/METADATA
rancher_api-0.3.0.dist-info/WHEEL
rancher_api-0.3.0.dist-info/top_level.txt
rancher_api-0.3.0.dist-info/RECORD
